{
  "$schema": "../node_modules/@tauri-apps/cli/config.schema.json",
  "productName": "Mobile Tavern",
  "version": "1.6.4",
  "identifier": "com.aitavern.app",
  "build": {
    "frontendDist": "../dist",
    "devUrl": "http://127.0.0.1:3000",
    "beforeDevCommand": "vite --host 127.0.0.1",
    "beforeBuildCommand": "npm run build"
  },
  "app": {
    "windows": [
      {
        "title": "Mobile Tavern",
        "width": 800,
        "height": 600,
        "resizable": true,
        "fullscreen": false
      }
    ],
    "security": {
      "csp": "default-src 'self'; script-src 'self' 'unsafe-inline'; style-src 'self' 'unsafe-inline'; font-src 'self' data:; img-src 'self' data: blob: https:; connect-src 'self' https: http://127.0.0.1:* http://localhost:* ws://127.0.0.1:* ws://localhost:*; media-src 'self' data: blob: https:; object-src 'none'; frame-src 'self' blob: data:; worker-src 'self' blob:; base-uri 'self'"
    }
  },
  "bundle": {
    "active": true,
    "targets": "all",
    "icon": [
      "icons/32x32.png",
      "icons/128x128.png",
      "icons/128x128@2x.png",
      "icons/icon.icns",
      "icons/icon.ico"
    ],
    "android": {
      "debugApplicationIdSuffix": ".debug"
    }
  }
}
